{
    "user": {
        "user_login": [],
        "user_add": [
            1
        ],
        "user_edit": [
            1
        ],
        "user_list": [
            1
        ],
        "user_view": [
            1
        ],
        "user_forget_password": [],
        "user_reset_password": []
    },
    "project": {
        "project_add": [
            1
        ],
        "project_edit": [
            1
        ],
        "project_list": [
            1
        ],
        "project_view": [
            1
        ],
        "project_active_list": [
            1
        ],
        "project_status_change": [
            1
        ],
        "project_delete": [
            1
        ]
    },
    "project_media": {
        "media_upload": [1],
        "media_list": [1],
        "media_view": [1],
        "media_delete": [1],
        "feature_image_upload": [1],
        "view_feature_image": [1]
    },
    "design": {
        "design_add": [1],
        "design_list": [1],
        "design_delete": [1]
    },
    "plan": {
        "plan_add": [1],
        "plan_list": [1],
        "plan_delete": [1]
    }
}
